{
  "annotations": {
    "list": [
      {
        "builtIn": 1,
        "datasource": "-- Grafana --",
        "enable": true,
        "hide": true,
        "iconColor": "rgba(0, 211, 255, 1)",
        "name": "Annotations & Alerts",
        "type": "dashboard"
      }
    ]
  },
  "editable": true,
  "gnetId": null,
  "graphTooltip": 0,
  "id": null,
  "links": [],
  "panels": [
    {
      "datasource": "Prometheus",
      "fieldConfig": {
        "defaults": {
          "color": { "mode": "palette-classic" },
          "custom": {
            "axisLabel": "",
            "axisPlacement": "auto",
            "barAlignment": 0,
            "drawStyle": "line",
            "fillOpacity": 10,
            "gradientMode": "none",
            "hideFrom": {
              "tooltip": false,
              "viz": false,
              "legend": false
            },
            "lineInterpolation": "linear",
            "lineWidth": 1,
            "pointSize": 5,
            "scaleDistribution": {
              "type": "linear"
            },
            "showPoints": "never",
            "spanNulls": false
          },
          "mappings": [],
          "thresholds": {
            "mode": "absolute",
            "steps": [
              { "color": "green", "value": null }
            ]
          },
          "unit": "reqps"
        }
      },
      "gridPos": { "h": 8, "w": 12, "x": 0, "y": 0 },
      "id": 1,
      "options": {
        "legend": {
          "calcs": ["mean", "max"],
          "displayMode": "table",
          "placement": "bottom"
        },
        "tooltip": {
          "mode": "single"
        }
      },
      "targets": [
        {
          "expr": "sum(rate(api_requests_total[5m])) by (endpoint)",
          "legendFormat": "{{ endpoint }}",
          "refId": "A"
        }
      ],
      "title": "Request Rate by Endpoint",
      "type": "timeseries"
    },
    {
      "datasource": "Prometheus",
      "fieldConfig": {
        "defaults": {
          "color": { "mode": "palette-classic" },
          "custom": {
            "axisLabel": "",
            "axisPlacement": "auto",
            "barAlignment": 0,
            "drawStyle": "line",
            "fillOpacity": 10,
            "gradientMode": "none",
            "hideFrom": {
              "tooltip": false,
              "viz": false,
              "legend": false
            },
            "lineInterpolation": "linear",
            "lineWidth": 1,
            "pointSize": 5,
            "scaleDistribution": {
              "type": "linear"
            },
            "showPoints": "never",
            "spanNulls": false
          },
          "mappings": [],
          "thresholds": {
            "mode": "absolute",
            "steps": [
              { "color": "green", "value": null }
            ]
          },
          "unit": "percentunit"
        }
      },
      "gridPos": { "h": 8, "w": 12, "x": 12, "y": 0 },
      "id": 2,
      "options": {
        "legend": {
          "calcs": ["mean", "last"],
          "displayMode": "table",
          "placement": "bottom"
        },
        "tooltip": {
          "mode": "single"
        }
      },
      "targets": [
        {
          "expr": "(sum(rate(api_requests_total{status=~\"5..\"}[5m])) / sum(rate(api_requests_total[5m])))",
          "legendFormat": "5xx Error Rate",
          "refId": "A"
        },
        {
          "expr": "(sum(rate(api_requests_total{status=~\"4..\"}[5m])) / sum(rate(api_requests_total[5m])))",
          "legendFormat": "4xx Error Rate",
          "refId": "B"
        }
      ],
      "title": "Error Rate",
      "type": "timeseries"
    },
    {
      "datasource": "Prometheus",
      "fieldConfig": {
        "defaults": {
          "color": { "mode": "palette-classic" },
          "custom": {
            "axisLabel": "",
            "axisPlacement": "auto",
            "barAlignment": 0,
            "drawStyle": "line",
            "fillOpacity": 10,
            "gradientMode": "none",
            "hideFrom": {
              "tooltip": false,
              "viz": false,
              "legend": false
            },
            "lineInterpolation": "linear",
            "lineWidth": 1,
            "pointSize": 5,
            "scaleDistribution": {
              "type": "linear"
            },
            "showPoints": "never",
            "spanNulls": false
          },
          "mappings": [],
          "thresholds": {
            "mode": "absolute",
            "steps": [
              { "color": "green", "value": null },
              { "color": "yellow", "value": 1 },
              { "color": "red", "value": 2 }
            ]
          },
          "unit": "s"
        }
      },
      "gridPos": { "h": 8, "w": 24, "x": 0, "y": 8 },
      "id": 3,
      "options": {
        "legend": {
          "calcs": ["mean", "max", "p95", "p99"],
          "displayMode": "table",
          "placement": "bottom"
        },
        "tooltip": {
          "mode": "single"
        }
      },
      "targets": [
        {
          "expr": "histogram_quantile(0.50, sum(rate(api_request_duration_seconds_bucket[5m])) by (le))",
          "legendFormat": "p50",
          "refId": "A"
        },
        {
          "expr": "histogram_quantile(0.95, sum(rate(api_request_duration_seconds_bucket[5m])) by (le))",
          "legendFormat": "p95",
          "refId": "B"
        },
        {
          "expr": "histogram_quantile(0.99, sum(rate(api_request_duration_seconds_bucket[5m])) by (le))",
          "legendFormat": "p99",
          "refId": "C"
        }
      ],
      "title": "Request Latency Percentiles (All Endpoints)",
      "type": "timeseries"
    },
    {
      "datasource": "Prometheus",
      "fieldConfig": {
        "defaults": {
          "color": { "mode": "palette-classic" },
          "custom": {
            "axisLabel": "",
            "axisPlacement": "auto",
            "barAlignment": 0,
            "drawStyle": "line",
            "fillOpacity": 10,
            "gradientMode": "none",
            "hideFrom": {
              "tooltip": false,
              "viz": false,
              "legend": false
            },
            "lineInterpolation": "linear",
            "lineWidth": 1,
            "pointSize": 5,
            "scaleDistribution": {
              "type": "linear"
            },
            "showPoints": "never",
            "spanNulls": false
          },
          "mappings": [],
          "thresholds": {
            "mode": "absolute",
            "steps": [
              { "color": "green", "value": null }
            ]
          },
          "unit": "s"
        }
      },
      "gridPos": { "h": 8, "w": 12, "x": 0, "y": 16 },
      "id": 4,
      "options": {
        "legend": {
          "calcs": ["mean", "p95"],
          "displayMode": "table",
          "placement": "bottom"
        },
        "tooltip": {
          "mode": "single"
        }
      },
      "targets": [
        {
          "expr": "histogram_quantile(0.95, sum(rate(api_request_duration_seconds_bucket[5m])) by (le, endpoint))",
          "legendFormat": "{{ endpoint }}",
          "refId": "A"
        }
      ],
      "title": "Request Latency p95 by Endpoint",
      "type": "timeseries"
    },
    {
      "datasource": "Prometheus",
      "fieldConfig": {
        "defaults": {
          "color": { "mode": "palette-classic" },
          "custom": {
            "axisLabel": "",
            "axisPlacement": "auto",
            "barAlignment": 0,
            "drawStyle": "line",
            "fillOpacity": 10,
            "gradientMode": "none",
            "hideFrom": {
              "tooltip": false,
              "viz": false,
              "legend": false
            },
            "lineInterpolation": "linear",
            "lineWidth": 1,
            "pointSize": 5,
            "scaleDistribution": {
              "type": "linear"
            },
            "showPoints": "never",
            "spanNulls": false
          },
          "mappings": [],
          "thresholds": {
            "mode": "absolute",
            "steps": [
              { "color": "green", "value": null }
            ]
          },
          "unit": "short"
        }
      },
      "gridPos": { "h": 8, "w": 12, "x": 12, "y": 16 },
      "id": 5,
      "options": {
        "legend": {
          "calcs": ["mean", "max"],
          "displayMode": "table",
          "placement": "bottom"
        },
        "tooltip": {
          "mode": "single"
        }
      },
      "targets": [
        {
          "expr": "sum(api_requests_in_progress) by (endpoint)",
          "legendFormat": "{{ endpoint }}",
          "refId": "A"
        }
      ],
      "title": "In-Progress Requests by Endpoint",
      "type": "timeseries"
    },
    {
      "datasource": "Prometheus",
      "fieldConfig": {
        "defaults": {
          "color": { "mode": "palette-classic" },
          "custom": {
            "axisLabel": "",
            "axisPlacement": "auto",
            "barAlignment": 0,
            "drawStyle": "line",
            "fillOpacity": 10,
            "gradientMode": "none",
            "hideFrom": {
              "tooltip": false,
              "viz": false,
              "legend": false
            },
            "lineInterpolation": "linear",
            "lineWidth": 1,
            "pointSize": 5,
            "scaleDistribution": {
              "type": "linear"
            },
            "showPoints": "never",
            "spanNulls": false
          },
          "mappings": [],
          "thresholds": {
            "mode": "absolute",
            "steps": [
              { "color": "green", "value": null }
            ]
          },
          "unit": "short"
        }
      },
      "gridPos": { "h": 8, "w": 12, "x": 0, "y": 24 },
      "id": 6,
      "options": {
        "legend": {
          "calcs": ["mean", "sum"],
          "displayMode": "table",
          "placement": "bottom"
        },
        "tooltip": {
          "mode": "single"
        }
      },
      "targets": [
        {
          "expr": "rate(api_key_rate_limit_exceeded[5m])",
          "legendFormat": "Rate Limit Exceeded",
          "refId": "A"
        },
        {
          "expr": "rate(api_key_quota_exceeded[5m])",
          "legendFormat": "Quota Exceeded",
          "refId": "B"
        }
      ],
      "title": "Rate Limiting & Quota",
      "type": "timeseries"
    },
    {
      "datasource": "Prometheus",
      "fieldConfig": {
        "defaults": {
          "color": { "mode": "palette-classic" },
          "custom": {
            "axisLabel": "",
            "axisPlacement": "auto",
            "barAlignment": 0,
            "drawStyle": "line",
            "fillOpacity": 10,
            "gradientMode": "none",
            "hideFrom": {
              "tooltip": false,
              "viz": false,
              "legend": false
            },
            "lineInterpolation": "linear",
            "lineWidth": 1,
            "pointSize": 5,
            "scaleDistribution": {
              "type": "linear"
            },
            "showPoints": "never",
            "spanNulls": false
          },
          "mappings": [],
          "thresholds": {
            "mode": "absolute",
            "steps": [
              { "color": "green", "value": null }
            ]
          },
          "unit": "percentunit"
        }
      },
      "gridPos": { "h": 8, "w": 12, "x": 12, "y": 24 },
      "id": 7,
      "options": {
        "legend": {
          "calcs": ["mean", "last"],
          "displayMode": "table",
          "placement": "bottom"
        },
        "tooltip": {
          "mode": "single"
        }
      },
      "targets": [
        {
          "expr": "(rate(webhook_sent_total{status=\"failure\"}[10m]) / rate(webhook_sent_total[10m]))",
          "legendFormat": "Webhook Failure Rate",
          "refId": "A"
        }
      ],
      "title": "Webhook Delivery Success Rate",
      "type": "timeseries"
    },
    {
      "datasource": "Prometheus",
      "fieldConfig": {
        "defaults": {
          "color": { "mode": "palette-classic" },
          "custom": {
            "axisLabel": "",
            "axisPlacement": "auto",
            "barAlignment": 0,
            "drawStyle": "line",
            "fillOpacity": 10,
            "gradientMode": "none",
            "hideFrom": {
              "tooltip": false,
              "viz": false,
              "legend": false
            },
            "lineInterpolation": "linear",
            "lineWidth": 1,
            "pointSize": 5,
            "scaleDistribution": {
              "type": "linear"
            },
            "showPoints": "never",
            "spanNulls": false
          },
          "mappings": [],
          "thresholds": {
            "mode": "absolute",
            "steps": [
              { "color": "green", "value": null }
            ]
          },
          "unit": "s"
        }
      },
      "gridPos": { "h": 8, "w": 12, "x": 0, "y": 32 },
      "id": 8,
      "options": {
        "legend": {
          "calcs": ["mean", "max"],
          "displayMode": "table",
          "placement": "bottom"
        },
        "tooltip": {
          "mode": "single"
        }
      },
      "targets": [
        {
          "expr": "histogram_quantile(0.95, rate(storage_operation_duration_seconds_bucket[10m]))",
          "legendFormat": "Storage Operations (p95)",
          "refId": "A"
        }
      ],
      "title": "Storage Operation Duration",
      "type": "timeseries"
    },
    {
      "datasource": "Prometheus",
      "fieldConfig": {
        "defaults": {
          "color": { "mode": "palette-classic" },
          "custom": {
            "axisLabel": "",
            "axisPlacement": "auto",
            "barAlignment": 0,
            "drawStyle": "line",
            "fillOpacity": 10,
            "gradientMode": "none",
            "hideFrom": {
              "tooltip": false,
              "viz": false,
              "legend": false
            },
            "lineInterpolation": "linear",
            "lineWidth": 1,
            "pointSize": 5,
            "scaleDistribution": {
              "type": "linear"
            },
            "showPoints": "never",
            "spanNulls": false
          },
          "mappings": [],
          "thresholds": {
            "mode": "absolute",
            "steps": [
              { "color": "green", "value": null }
            ]
          },
          "unit": "percentunit"
        }
      },
      "gridPos": { "h": 8, "w": 12, "x": 12, "y": 32 },
      "id": 9,
      "options": {
        "legend": {
          "calcs": ["mean", "last"],
          "displayMode": "table",
          "placement": "bottom"
        },
        "tooltip": {
          "mode": "single"
        }
      },
      "targets": [
        {
          "expr": "(rate(cache_operations_total{operation=\"hit\"}[10m]) / rate(cache_operations_total{operation=~\"hit|miss\"}[10m]))",
          "legendFormat": "Cache Hit Rate",
          "refId": "A"
        },
        {
          "expr": "(rate(cache_operations_total{operation=\"miss\"}[10m]) / rate(cache_operations_total{operation=~\"hit|miss\"}[10m]))",
          "legendFormat": "Cache Miss Rate",
          "refId": "B"
        }
      ],
      "title": "Cache Performance",
      "type": "timeseries"
    },
    {
      "datasource": "Prometheus",
      "fieldConfig": {
        "defaults": {
          "color": { "mode": "palette-classic" },
          "custom": {
            "align": "auto",
            "displayMode": "auto"
          },
          "mappings": [],
          "thresholds": {
            "mode": "absolute",
            "steps": [
              { "color": "green", "value": null }
            ]
          }
        }
      },
      "gridPos": { "h": 10, "w": 24, "x": 0, "y": 40 },
      "id": 10,
      "options": {
        "showHeader": true,
        "sortBy": [
          {
            "desc": true,
            "displayName": "Request Rate"
          }
        ]
      },
      "targets": [
        {
          "expr": "sum(rate(api_requests_total[5m])) by (endpoint, method, status)",
          "format": "table",
          "instant": true,
          "refId": "A"
        }
      ],
      "title": "API Endpoint Performance Summary",
      "transformations": [
        {
          "id": "organize",
          "options": {
            "excludeByName": {
              "Time": true
            },
            "indexByName": {},
            "renameByName": {
              "endpoint": "Endpoint",
              "method": "Method",
              "status": "Status",
              "Value": "Request Rate (req/s)"
            }
          }
        }
      ],
      "type": "table"
    }
  ],
  "refresh": "30s",
  "schemaVersion": 27,
  "style": "dark",
  "tags": ["transcode-flow", "api", "performance"],
  "templating": {
    "list": []
  },
  "time": {
    "from": "now-1h",
    "to": "now"
  },
  "timepicker": {},
  "timezone": "",
  "title": "Transcode Flow - API Performance",
  "uid": "api-performance",
  "version": 1
}
